How2jJavaGaojiYingyongJiaocheng/README.md
How2jJavaGaojiYingyongJiaocheng/__init__.py
How2jJavaGaojiYingyongJiaocheng/__main__.py
How2jJavaGaojiYingyongJiaocheng/file.epub
How2jJavaGaojiYingyongJiaocheng/index.html
How2jJavaGaojiYingyongJiaocheng/css/__init__.py
How2jJavaGaojiYingyongJiaocheng/css/annotations.css
How2jJavaGaojiYingyongJiaocheng/css/main.css
How2jJavaGaojiYingyongJiaocheng/css/normalize.css
How2jJavaGaojiYingyongJiaocheng/css/popup.css
How2jJavaGaojiYingyongJiaocheng/font/__init__.py
How2jJavaGaojiYingyongJiaocheng/font/fontello.eot
How2jJavaGaojiYingyongJiaocheng/font/fontello.svg
How2jJavaGaojiYingyongJiaocheng/font/fontello.ttf
How2jJavaGaojiYingyongJiaocheng/font/fontello.woff
How2jJavaGaojiYingyongJiaocheng/img/__init__.py
How2jJavaGaojiYingyongJiaocheng/img/annotator-glyph-sprite.png
How2jJavaGaojiYingyongJiaocheng/img/annotator-icon-sprite.png
How2jJavaGaojiYingyongJiaocheng/img/apple-touch-icon.png
How2jJavaGaojiYingyongJiaocheng/img/cancelfullscreen.png
How2jJavaGaojiYingyongJiaocheng/img/close.png
How2jJavaGaojiYingyongJiaocheng/img/fullscreen.png
How2jJavaGaojiYingyongJiaocheng/img/loader.gif
How2jJavaGaojiYingyongJiaocheng/img/menu-icon.png
How2jJavaGaojiYingyongJiaocheng/img/save.png
How2jJavaGaojiYingyongJiaocheng/img/saved.png
How2jJavaGaojiYingyongJiaocheng/img/settings-s.png
How2jJavaGaojiYingyongJiaocheng/img/settings.png
How2jJavaGaojiYingyongJiaocheng/img/star.png
How2jJavaGaojiYingyongJiaocheng/js/__init__.py
How2jJavaGaojiYingyongJiaocheng/js/epub.js
How2jJavaGaojiYingyongJiaocheng/js/epub.min.js
How2jJavaGaojiYingyongJiaocheng/js/epub.min.map
How2jJavaGaojiYingyongJiaocheng/js/hooks.min.js
How2jJavaGaojiYingyongJiaocheng/js/hooks.min.map
How2jJavaGaojiYingyongJiaocheng/js/reader.js
How2jJavaGaojiYingyongJiaocheng/js/reader.js.map
How2jJavaGaojiYingyongJiaocheng/js/reader.min.js
How2jJavaGaojiYingyongJiaocheng/js/reader.min.map
How2jJavaGaojiYingyongJiaocheng/js/hooks/__init__.py
how2j_java_gaoji_yingyong_jiaocheng-2024.3.5.0.dist-info/METADATA
how2j_java_gaoji_yingyong_jiaocheng-2024.3.5.0.dist-info/WHEEL
how2j_java_gaoji_yingyong_jiaocheng-2024.3.5.0.dist-info/entry_points.txt
how2j_java_gaoji_yingyong_jiaocheng-2024.3.5.0.dist-info/top_level.txt
how2j_java_gaoji_yingyong_jiaocheng-2024.3.5.0.dist-info/RECORD
